webscout/AIauto.py
webscout/AIbase.py
webscout/AIutel.py
webscout/Bard.py
webscout/__init__.py
webscout/__main__.py
webscout/cli.py
webscout/client.py
webscout/conversation.py
webscout/exceptions.py
webscout/model_fetcher.py
webscout/models.py
webscout/optimizers.py
webscout/prompt_manager.py
webscout/sanitize.py
webscout/update_checker.py
webscout/utils.py
webscout/version.py
webscout/version.py.bak
webscout/Extra/__init__.py
webscout/Extra/gguf.py
webscout/Extra/proxy_manager.py
webscout/Extra/weather.py
webscout/Extra/weather_ascii.py
webscout/Extra/GitToolkit/__init__.py
webscout/Extra/GitToolkit/gitapi/__init__.py
webscout/Extra/GitToolkit/gitapi/gist.py
webscout/Extra/GitToolkit/gitapi/organization.py
webscout/Extra/GitToolkit/gitapi/repository.py
webscout/Extra/GitToolkit/gitapi/search.py
webscout/Extra/GitToolkit/gitapi/trending.py
webscout/Extra/GitToolkit/gitapi/user.py
webscout/Extra/GitToolkit/gitapi/utils.py
webscout/Extra/YTToolkit/README.md
webscout/Extra/YTToolkit/YTdownloader.py
webscout/Extra/YTToolkit/__init__.py
webscout/Extra/YTToolkit/transcriber.py
webscout/Extra/YTToolkit/ytapi/README.md
webscout/Extra/YTToolkit/ytapi/__init__.py
webscout/Extra/YTToolkit/ytapi/captions.py
webscout/Extra/YTToolkit/ytapi/channel.py
webscout/Extra/YTToolkit/ytapi/errors.py
webscout/Extra/YTToolkit/ytapi/extras.py
webscout/Extra/YTToolkit/ytapi/hashtag.py
webscout/Extra/YTToolkit/ytapi/https.py
webscout/Extra/YTToolkit/ytapi/patterns.py
webscout/Extra/YTToolkit/ytapi/playlist.py
webscout/Extra/YTToolkit/ytapi/pool.py
webscout/Extra/YTToolkit/ytapi/query.py
webscout/Extra/YTToolkit/ytapi/shorts.py
webscout/Extra/YTToolkit/ytapi/stream.py
webscout/Extra/YTToolkit/ytapi/suggestions.py
webscout/Extra/YTToolkit/ytapi/utils.py
webscout/Extra/YTToolkit/ytapi/video.py
webscout/Extra/tempmail/README.md
webscout/Extra/tempmail/__init__.py
webscout/Extra/tempmail/async_utils.py
webscout/Extra/tempmail/base.py
webscout/Extra/tempmail/cli.py
webscout-2026.1.31.dist-info/licenses/LICENSE.md
webscout-2026.1.31.dist-info/METADATA
webscout-2026.1.31.dist-info/WHEEL
webscout-2026.1.31.dist-info/entry_points.txt
webscout-2026.1.31.dist-info/top_level.txt
webscout-2026.1.31.dist-info/RECORD
