Metadata-Version: 2.4
Name: webscout
Version: 2026.1.31
Summary: Search for anything using Google, DuckDuckGo, phind.com, Contains AI models, can transcribe yt videos, temporary email and phone number generation, has TTS support, webai (terminal gpt and open interpreter) and offline LLMs and more
Author-email: OEvortex <koulabhay26@gmail.com>
License: Apache-2.0
Project-URL: Source, https://github.com/OEvortex/Webscout
Project-URL: Tracker, https://github.com/OEvortex/Webscout/issues
Project-URL: YouTube, https://youtube.com/@OEvortex
Keywords: search,ai,chatbot,llm,language-model,gpt,openai,gemini,claude,llama,search-engine,text-to-speech,tts,text-to-image,tti,weather,youtube,toolkit,utilities,web-search,duckduckgo,google,yep
Classifier: Development Status :: 5 - Production/Stable
Classifier: Intended Audience :: Developers
Classifier: Intended Audience :: End Users/Desktop
Classifier: Intended Audience :: Science/Research
Classifier: License :: OSI Approved :: Apache Software License
Classifier: Natural Language :: English
Classifier: Operating System :: OS Independent
Classifier: Operating System :: Microsoft :: Windows
Classifier: Operating System :: POSIX :: Linux
Classifier: Operating System :: MacOS :: MacOS X
Classifier: Programming Language :: Python :: 3
Classifier: Programming Language :: Python :: 3.9
Classifier: Programming Language :: Python :: 3.10
Classifier: Programming Language :: Python :: 3.11
Classifier: Programming Language :: Python :: 3.12
Classifier: Programming Language :: Python :: 3.13
Classifier: Programming Language :: Python :: Implementation :: CPython
Classifier: Topic :: Internet :: WWW/HTTP :: Indexing/Search
Classifier: Topic :: Software Development :: Libraries :: Python Modules
Classifier: Topic :: Text Processing :: Linguistic
Classifier: Topic :: Scientific/Engineering :: Artificial Intelligence
Classifier: Topic :: Communications
Classifier: Topic :: Utilities
Requires-Python: >=3.9
License-File: LICENSE.md
Requires-Dist: setuptools
Requires-Dist: wheel
Requires-Dist: pip
Requires-Dist: curl_cffi
Requires-Dist: nest-asyncio
Requires-Dist: colorama
Requires-Dist: rich
Requires-Dist: PyYAML
Requires-Dist: html5lib
Requires-Dist: psutil
Requires-Dist: aiohttp
Requires-Dist: litprinter
Requires-Dist: lxml>=5.2.2
Requires-Dist: pydantic
Provides-Extra: dev
Requires-Dist: ruff>=0.1.6; extra == "dev"
Requires-Dist: pytest>=7.4.2; extra == "dev"
Provides-Extra: api
Requires-Dist: fastapi; extra == "api"
Requires-Dist: uvicorn[standard]; extra == "api"
Requires-Dist: pydantic; extra == "api"
Requires-Dist: python-multipart; extra == "api"
Requires-Dist: tiktoken; extra == "api"
Requires-Dist: jinja2; extra == "api"
Requires-Dist: websockets>=11.0; extra == "api"
Requires-Dist: starlette; extra == "api"
Requires-Dist: regex; extra == "api"
Provides-Extra: parser
Requires-Dist: lxml>=5.2.2; extra == "parser"
Dynamic: license-file
